zoke/__init__.py
zoke/cli.py
zoke/config.py
zoke_cli-0.1.0.dist-info/METADATA
zoke_cli-0.1.0.dist-info/WHEEL
zoke_cli-0.1.0.dist-info/entry_points.txt
zoke_cli-0.1.0.dist-info/top_level.txt
zoke_cli-0.1.0.dist-info/RECORD
