Metadata-Version: 2.4
Name: zoke-cli
Version: 0.1.0
Summary: Convert natural language to shell commands using OpenAI
Author-email: Your Name <you@example.com>
License: MIT
Project-URL: Homepage, https://github.com/Zoron-AI/zoke-cli
Project-URL: Repository, https://github.com/Zoron-AI/zoke-cli
Classifier: Programming Language :: Python :: 3
Classifier: License :: OSI Approved :: MIT License
Classifier: Operating System :: OS Independent
Requires-Python: >=3.8
Requires-Dist: openai>=1.0.0
Dynamic: requires-python
